attrsx/__init__.py
attrsx/attrsx.py
attrsx/setup.py
attrsx/.paa.tracking/.paa.config
attrsx/.paa.tracking/.paa.version
attrsx/.paa.tracking/lsts_package_versions.yml
attrsx/.paa.tracking/notebook.ipynb
attrsx/.paa.tracking/package_licenses.json
attrsx/.paa.tracking/package_mapping.json
attrsx/.paa.tracking/release_notes.md
attrsx/.paa.tracking/version_logs.csv
attrsx/.paa.tracking/python_modules/attrsx.py
attrsx/mkdocs/mkdocs.yml
attrsx/mkdocs/docs/description.md
attrsx/mkdocs/docs/index.md
attrsx/mkdocs/docs/release-notes.md
attrsx/mkdocs/docs/css/extra.css
attrsx/mkdocs/site/404.html
attrsx/mkdocs/site/index.html
attrsx/mkdocs/site/sitemap.xml
attrsx/mkdocs/site/sitemap.xml.gz
attrsx/mkdocs/site/assets/images/favicon.png
attrsx/mkdocs/site/assets/javascripts/bundle.fe8b6f2b.min.js
attrsx/mkdocs/site/assets/javascripts/bundle.fe8b6f2b.min.js.map
attrsx/mkdocs/site/assets/javascripts/lunr/tinyseg.js
attrsx/mkdocs/site/assets/javascripts/lunr/wordcut.js
attrsx/mkdocs/site/assets/javascripts/lunr/min/lunr.ar.min.js
attrsx/mkdocs/site/assets/javascripts/lunr/min/lunr.da.min.js
attrsx/mkdocs/site/assets/javascripts/lunr/min/lunr.de.min.js
attrsx/mkdocs/site/assets/javascripts/lunr/min/lunr.du.min.js
attrsx/mkdocs/site/assets/javascripts/lunr/min/lunr.el.min.js
attrsx/mkdocs/site/assets/javascripts/lunr/min/lunr.es.min.js
attrsx/mkdocs/site/assets/javascripts/lunr/min/lunr.fi.min.js
attrsx/mkdocs/site/assets/javascripts/lunr/min/lunr.fr.min.js
attrsx/mkdocs/site/assets/javascripts/lunr/min/lunr.he.min.js
attrsx/mkdocs/site/assets/javascripts/lunr/min/lunr.hi.min.js
attrsx/mkdocs/site/assets/javascripts/lunr/min/lunr.hu.min.js
attrsx/mkdocs/site/assets/javascripts/lunr/min/lunr.hy.min.js
attrsx/mkdocs/site/assets/javascripts/lunr/min/lunr.it.min.js
attrsx/mkdocs/site/assets/javascripts/lunr/min/lunr.ja.min.js
attrsx/mkdocs/site/assets/javascripts/lunr/min/lunr.jp.min.js
attrsx/mkdocs/site/assets/javascripts/lunr/min/lunr.kn.min.js
attrsx-0.2.0.dist-info/licenses/LICENSE
attrsx-0.2.0.dist-info/METADATA
attrsx-0.2.0.dist-info/WHEEL
attrsx-0.2.0.dist-info/top_level.txt
attrsx-0.2.0.dist-info/RECORD
