Metadata-Version: 2.4
Name: attrsx
Version: 0.2.0
Summary: A lightweight extension of attrs that adds extras like logging.
Home-page: https://kiril-mordan.github.io/reusables/attrsx/
Author: Kyrylo Mordan
Author-email: parachute.repo@gmail.com
License: mit
Keywords: aa-paa-tool
Classifier: Development Status :: 3 - Alpha
Classifier: Intended Audience :: Developers
Classifier: Intended Audience :: Science/Research
Classifier: Programming Language :: Python :: 3
Classifier: Programming Language :: Python :: 3.9
Classifier: Programming Language :: Python :: 3.10
Classifier: Programming Language :: Python :: 3.11
Classifier: Programming Language :: Python :: 3.12
Classifier: License :: OSI Approved :: MIT License
Classifier: Topic :: Scientific/Engineering
License-File: LICENSE
Requires-Dist: attrs>=22.2.0
Dynamic: author
Dynamic: author-email
Dynamic: classifier
Dynamic: description
Dynamic: description-content-type
Dynamic: home-page
Dynamic: keywords
Dynamic: license
Dynamic: license-file
Dynamic: requires-dist
Dynamic: summary
